{
  "type": "Feature",
  "properties": {
    "gn:admin1_code":"16.0",
    "gn:asciiname":"Pulo Anna Village",
    "gn:country_code":"PW",
    "gn:dem":9,
    "gn:feature_class":"P",
    "gn:feature_code":"PPL",
    "gn:name":"Pulo Anna Village",
    "gn:population":0,
    "gn:timezone":"Pacific/Palau",
    "iso:country":"PW",
    "name:sov_x_preferred":[
        "Puro Village"
    ],
    "wof:name":"Pulo Anna Village",
    "wof:placetype":"locality"
},
  "geometry": {"coordinates":[131.94901000000002,4.65404],"type":"Point"}
}