{
  "type": "Feature",
  "properties": {
    "gn:admin1_code":"1.0",
    "gn:asciiname":"Elauesachel Hamlet",
    "gn:country_code":"PW",
    "gn:dem":34,
    "gn:elevation":"30.0",
    "gn:feature_class":"P",
    "gn:feature_code":"PPL",
    "gn:name":"Elauesachel Hamlet",
    "gn:population":0,
    "gn:timezone":"Pacific/Palau",
    "iso:country":"PW",
    "wof:name":"Elauesachel Hamlet",
    "wof:placetype":"locality"
},
  "geometry": {"coordinates":[134.50616000000002,7.45743],"type":"Point"}
}