{
  "type": "Feature",
  "properties": {
    "gn:admin1_code":"16.0",
    "gn:asciiname":"Sonsorol Village",
    "gn:country_code":"PW",
    "gn:dem":7,
    "gn:feature_class":"P",
    "gn:feature_code":"PPLA",
    "gn:name":"Sonsorol Village",
    "gn:population":30,
    "gn:timezone":"Pacific/Palau",
    "iso:country":"PW",
    "name:ara_x_preferred":[
        "\u062f\u0648\u0646\u062c\u0648\u0633\u0627\u0631\u0648"
    ],
    "name:fra_x_preferred":[
        "Dongosaro"
    ],
    "name:nld_x_preferred":[
        "Dongosaro"
    ],
    "name:pau_x_preferred":[
        "Sonsorol"
    ],
    "name:pol_x_preferred":[
        "Dongosaru"
    ],
    "name:sov_x_preferred":[
        "Dongosaro"
    ],
    "name:spa_x_preferred":[
        "Dongosaru"
    ],
    "wof:name":"Sonsorol Village",
    "wof:placetype":"locality",
    "wof:population":30
},
  "geometry": {"coordinates":[132.21943000000002,5.32608],"type":"Point"}
}