{
  "type": "Feature",
  "properties": {
    "gn:country":"PW",
    "gn:fcode":"RGN",
    "gn:population":464,
    "iso:country":"PW",
    "qs:name":"Babeldaob West - Ngatapang State",
    "qs:photos_9r":0,
    "qs:photos_sr":0,
    "qs:pop_sr":"2",
    "wof:name":"Babeldaob West - Ngatapang State",
    "wof:placetype":"locality",
    "wof:population":464
},
  "geometry": {"coordinates":[134.52099999999999,7.4869],"type":"Point"}
}