{
  "type": "Feature",
  "properties": {
    "gn:admin1_code":"2.0",
    "gn:asciiname":"Ordomel Hamlet",
    "gn:country_code":"PW",
    "gn:dem":8,
    "gn:elevation":"8.0",
    "gn:feature_class":"P",
    "gn:feature_code":"PPL",
    "gn:name":"Ordomel Hamlet",
    "gn:population":0,
    "gn:timezone":"Pacific/Palau",
    "iso:country":"PW",
    "wof:name":"Ordomel Hamlet",
    "wof:placetype":"locality"
},
  "geometry": {"coordinates":[134.55520000000001,7.38111],"type":"Point"}
}