{
  "type": "Feature",
  "properties": {
    "gn:admin1_code":"6.0",
    "gn:asciiname":"Echang Hamlet",
    "gn:country_code":"PW",
    "gn:dem":24,
    "gn:elevation":"20.0",
    "gn:feature_class":"P",
    "gn:feature_code":"PPL",
    "gn:name":"Echang Hamlet",
    "gn:population":0,
    "gn:timezone":"Pacific/Palau",
    "iso:country":"PW",
    "name:und_x_variant":[
        "Tobi Islanders Village",
        "Eang",
        "Sonsorol Islanders Village"
    ],
    "wof:name":"Echang Hamlet",
    "wof:placetype":"locality"
},
  "geometry": {"coordinates":[134.45289,7.34661],"type":"Point"}
}