{
  "type": "Feature",
  "properties": {
    "gn:admin1_code":"7.0",
    "gn:asciiname":"Ngerulmud",
    "gn:country_code":"PW",
    "gn:dem":72,
    "gn:feature_class":"P",
    "gn:feature_code":"PPLC",
    "gn:name":"Ngerulmud",
    "gn:population":0,
    "gn:timezone":"Pacific/Palau",
    "iso:country":"PW",
    "name:eng_x_preferred":[
        "Ngerulmud"
    ],
    "name:kor_x_preferred":[
        "\uc751\uac8c\ub8f0\ubb34\ub4dc"
    ],
    "name:rus_x_preferred":[
        "\u041d\u0433\u0435\u0440\u0443\u043b\u043c\u0443\u0434"
    ],
    "wof:name":"Ngerulmud",
    "wof:placetype":"locality"
},
  "geometry": {"coordinates":[134.62379999999999,7.50077],"type":"Point"}
}