{
  "type": "Feature",
  "properties": {
    "iso:country":"PW",
    "name:ara_x_preferred":[
        "\u0648\u0644\u0627\u064a\u0629 \u0623\u064a\u0631\u0627\u064a"
    ],
    "name:deu_x_preferred":[
        "Airai"
    ],
    "name:est_x_preferred":[
        "Airai osariik"
    ],
    "name:fin_x_preferred":[
        "Airai"
    ],
    "name:fra_x_preferred":[
        "Airai"
    ],
    "name:hye_x_preferred":[
        "\u0531\u0575\u0580\u0561\u0575"
    ],
    "name:ind_x_preferred":[
        "Airai"
    ],
    "name:ita_x_preferred":[
        "Airai"
    ],
    "name:jpn_x_preferred":[
        "\u30a2\u30a4\u30e9\u30a4\u5dde"
    ],
    "name:kat_x_preferred":[
        "\u10d0\u10d8\u10e0\u10d0\u10d8"
    ],
    "name:kor_x_preferred":[
        "\uc544\uc774\ub77c\uc774\uc8fc"
    ],
    "name:lit_x_preferred":[
        "Airajus"
    ],
    "name:mkd_x_preferred":[
        "\u0410\u0458\u0440\u0430\u0458"
    ],
    "name:mrj_x_preferred":[
        "\u0410\u0438\u0440\u0430\u0438"
    ],
    "name:nld_x_preferred":[
        "Airai"
    ],
    "name:nor_x_preferred":[
        "Airai"
    ],
    "name:pol_x_preferred":[
        "Airai"
    ],
    "name:por_x_preferred":[
        "Airai"
    ],
    "name:srp_x_preferred":[
        "\u0410\u0438\u0440\u0430\u0438"
    ],
    "name:swe_x_preferred":[
        "Airai"
    ],
    "name:urd_x_preferred":[
        "\u0622\u0626\u0631\u0627\u0626\u06cc"
    ],
    "name:vie_x_preferred":[
        "Airai"
    ],
    "name:zho_x_preferred":[
        "\u827e\u62c9\u4f0a\u5dde"
    ],
    "qs:gn_pop":0,
    "qs:name":"Airai",
    "qs:name_adm0":"Palau",
    "qs:name_adm1":"Airai",
    "qs:photos":175,
    "qs:photos_1k":35,
    "qs:photos_9k":1,
    "qs:photos_9r":4,
    "qs:photos_all":175,
    "qs:photos_sr":4,
    "qs:placetype":"Town",
    "qs:pop_sr":"0",
    "qs:woe_adm0":23424927,
    "wof:name":"Airai",
    "wof:placetype":"locality"
},
  "geometry": {"coordinates":[134.555375,7.367052],"type":"Point"}
}