{
  "type": "Feature",
  "properties": {
    "iso:country":"PW",
    "qs:gn_pop":0,
    "qs:name":"Airai",
    "qs:name_adm0":"Palau",
    "qs:name_adm1":"Airai",
    "qs:photos":175,
    "qs:photos_1k":35,
    "qs:photos_9k":1,
    "qs:photos_9r":4,
    "qs:photos_all":175,
    "qs:photos_sr":4,
    "qs:placetype":"Town",
    "qs:pop_sr":"0",
    "qs:woe_adm0":23424927,
    "wof:name":"Airai",
    "wof:placetype":"locality"
},
  "geometry": {"coordinates":[134.555375,7.367052],"type":"Point"}
}