{
  "type": "Feature",
  "properties": {
    "gn:admin1_code":"9.0",
    "gn:asciiname":"Ngriil Hamlet",
    "gn:cc2":"PW",
    "gn:country_code":"PW",
    "gn:dem":41,
    "gn:elevation":"35.0",
    "gn:feature_class":"P",
    "gn:feature_code":"PPL",
    "gn:name":"Ngriil Hamlet",
    "gn:population":0,
    "gn:timezone":"Pacific/Palau",
    "iso:country":"PW",
    "name:und_x_variant":[
        "Ngril",
        "Chiyou",
        "Ngriel",
        "Ngriil"
    ],
    "wof:name":"Ngriil Hamlet",
    "wof:placetype":"locality"
},
  "geometry": {"coordinates":[134.63609,7.69032],"type":"Point"}
}