{
  "type": "Feature",
  "properties": {
    "gn:admin1_code":"6.0",
    "gn:asciiname":"Ngerkeseuaol Hamlet",
    "gn:country_code":"PW",
    "gn:dem":48,
    "gn:elevation":"40.0",
    "gn:feature_class":"P",
    "gn:feature_code":"PPL",
    "gn:name":"Ngerkeseuaol Hamlet",
    "gn:population":0,
    "gn:timezone":"Pacific/Palau",
    "iso:country":"PW",
    "name:und_x_variant":[
        "Kesauaol",
        "Ngerkeseoul",
        "Ngarekesauaol",
        "Atekasabra",
        "Aiekasaol",
        "Ngerkesewaol",
        "Kesaiaol",
        "Ngarakassoul",
        "Atekasaoru",
        "Atekasabru",
        "Arakasoaol",
        "Aiekasol"
    ],
    "wof:name":"Ngerkeseuaol Hamlet",
    "wof:placetype":"locality"
},
  "geometry": {"coordinates":[134.48948999999999,7.34301],"type":"Point"}
}