{
  "type": "Feature",
  "properties": {
    "gn:admin1_code":"2.0",
    "gn:asciiname":"Ngetkib Hamlet",
    "gn:country_code":"PW",
    "gn:dem":23,
    "gn:elevation":"20.0",
    "gn:feature_class":"P",
    "gn:feature_code":"PPL",
    "gn:name":"Ngetkib Hamlet",
    "gn:population":0,
    "gn:timezone":"Pacific/Palau",
    "iso:country":"PW",
    "name:und_x_variant":[
        "Aakip",
        "Gatkip",
        "Ngetkip",
        "Gadkip",
        "Itkib",
        "Ngetgip",
        "Gakkibu",
        "Atki\u00edp",
        "Ngtk\u00edp",
        "Ngatkip",
        "Gakip",
        "Adkip",
        "Ngetkib"
    ],
    "wof:name":"Ngetkib Hamlet",
    "wof:placetype":"locality"
},
  "geometry": {"coordinates":[134.51438999999999,7.36438],"type":"Point"}
}