{
  "type": "Feature",
  "properties": {
    "gn:country":"PW",
    "gn:fcode":"PPL",
    "gn:pop":320,
    "iso:country":"PW",
    "name:deu_x_preferred":[
        "Angaur"
    ],
    "name:eng_x_preferred":[
        "Angaur"
    ],
    "name:fin_x_preferred":[
        "Angaur"
    ],
    "name:ita_x_preferred":[
        "Angaur"
    ],
    "name:jpn_x_preferred":[
        "\u30a2\u30f3\u30ac\u30a6\u30eb\u5dde"
    ],
    "name:nor_x_preferred":[
        "Angaur"
    ],
    "name:por_x_preferred":[
        "Angaur"
    ],
    "name:spa_x_preferred":[
        "Angaur"
    ],
    "name:swe_x_preferred":[
        "Angaur"
    ],
    "name:unk_x_variant":[
        "Delutaog"
    ],
    "name:zho_x_preferred":[
        "\u5b89\u52a0\u723e"
    ],
    "qs:name":"Angaur",
    "qs:photos_9r":0,
    "qs:photos_sr":0,
    "qs:pop_sr":"2",
    "wd:wordcount":634,
    "wof:name":"Angaur",
    "wof:placetype":"locality",
    "wof:population":320
},
  "geometry": {"coordinates":[134.13132999999999,6.90331],"type":"Point"}
}